{"type":"FeatureCollection","features":[
  {"type":"Feature","id":"USA-WA","properties":{"fips":"41","name":"Washington"},"geometry":{"type":"Polygon","coordinates":[[[
              -123.31218053812267,
              49.00975203501844
            ],
            [
              -117.02555227725632,
              49.00998040434476
            ],
            [
              -117.03613209490624,
              46.47069454843199
            ],
            [
              -117.05729173020606,
              46.38318522606505
            ],
            [
              -117.03762441077636,
              46.34302652430611
            ],
            [
              -117.02244949596522,
              46.30460161655927
            ],
            [
              -116.96174983672097,
              46.255658154138246
            ],
            [
              -116.96174983672097,
              46.20667097011628
            ],
            [
              -116.91622509228758,
              46.164647153974954
            ],
            [
              -116.96680814165802,
              46.09453606767843
            ],
            [
              -116.94151661697279,
              46.05242657723085
            ],
            [
              -116.91116678735052,
              45.99623060783472
            ],
            [
              -118.9794029019458,
              45.99974452949786
            ],
            [
              -119.13060551332838,
              45.932151686796175
            ],
            [
              -119.29039932285721,
              45.93932142626366
            ],
            [
              -119.46565704943697,
              45.92498102034108
            ],
            [
              -119.58421374682948,
              45.92498102034108
            ],
            [
              -119.68730652717043,
              45.853223369844784
            ],
            [
              -119.89864672687006,
              45.838860715165
            ],
            [
              -120.10998692656938,
              45.77418287782825
            ],
            [
              -120.21307970691032,
              45.74541306698762
            ],
            [
              -120.47596629678043,
              45.695030201953244
            ],
            [
              -120.60483227220678,
              45.73821829638129
            ],
            [
              -120.72276673614654,
              45.70942994219007
            ],
            [
              -120.86194198960706,
              45.669821732157004
            ],
            [
              -120.91348837977786,
              45.63739415233732
            ],
            [
              -121.05781827225545,
              45.64820543189742
            ],
            [
              -121.14544713554548,
              45.6085538737251
            ],
            [
              -121.20214816473305,
              45.615765334269554
            ],
            [
              -121.22276672080136,
              45.677025311119735
            ],
            [
              -121.36709661327896,
              45.70942994219007
            ],
            [
              -121.44441619853482,
              45.68062675289363
            ],
            [
              -121.52689042280778,
              45.72382597365069
            ],
            [
              -121.67637495430245,
              45.69863048471271
            ],
            [
              -121.82070484678005,
              45.70942994219007
            ],
            [
              -121.92895226613808,
              45.6590146251645
            ],
            [
              -122.093900714684,
              45.59412817082378
            ],
            [
              -122.19699349502527,
              45.58691392845674
            ],
            [
              -122.29493163634913,
              45.55082880726826
            ],
            [
              -122.37225122160503,
              45.57248266186602
            ],
            [
              -122.74338523083316,
              45.640998144002225
            ],
            [
              -122.78987453472676,
              45.77949762997062
            ],
            [
              -122.80478409517494,
              45.95080479044509
            ],
            [
              -122.9538796996558,
              46.106080524605574
            ],
            [
              -123.16261354592936,
              46.18871590715844
            ],
            [
              -123.25207098273847,
              46.14741370063041
            ],
            [
              -123.43098570811614,
              46.17839324649947
            ],
            [
              -123.47571438946021,
              46.26607389718143
            ],
            [
              -123.72917691707829,
              46.26092008802064
            ],
            [
              -123.88572730178325,
              46.24030000631046
            ],
            [
              -124.01991334581638,
              46.30213699555733
            ],
            [
              -124.07955158760907,
              46.27638006201076
            ],
            [
              -123.98762481503597,
              46.6823148586966
            ],
            [
              -124.27407970061083,
              47.33159586702871
            ],
            [
              -124.470434472045,
              47.74880665004764
            ],
            [
              -124.724759298627,
              48.02449585677934
            ],
            [
              -124.73379969665883,
              48.4867386672787
            ]
          ],
          "type": "LineString"
        },
        "id": 0
      },
      {
        "type": "Feature",
        "properties": {},
        "geometry": {
          "coordinates": [
            [
              -124.73317794047423,
              48.48670374572396
            ],
            [
              -124.72529258352371,
              48.493091124080934
            ]
          ],
          "type": "LineString"
        }
      },
      {
        "type": "Feature",
        "properties": {},
        "geometry": {
          "coordinates": [
            [
              -123.31564365015743,
              49.00742320112917
            ],
            [
              -123.01586673215965,
              48.83116939134928
            ],
            [
              -123.0079778658965,
              48.77921164464021
            ],
            [
              -123.25253272005263,
              48.69596726212856
            ],
            [
              -123.14997745863239,
              48.42970537645479
            ],
            [
              -123.25253272005263,
              48.288175517769616
            ],
            [
              -123.52864303926103,
              48.21989124993024
            ],
            [
              -124.73563957751506,
              48.482024076769136
            ]
          ],
          "type": "LineString"
        }
      }
    ]
  }